izihawa_ipfs_api/__init__.py
izihawa_ipfs_api-1.0.7.dist-info/LICENSE
izihawa_ipfs_api-1.0.7.dist-info/METADATA
izihawa_ipfs_api-1.0.7.dist-info/WHEEL
izihawa_ipfs_api-1.0.7.dist-info/top_level.txt
izihawa_ipfs_api-1.0.7.dist-info/RECORD
